[{"is_top_nine": false, "top_nine_rank": null, "location_name": "Caesars Palace", "location_id": "127958949", "media_size": "581.975", "download_url": "https://scontent-mrs1-1.cdninstagram.com/vp/0fccad5b4280d3dd4e1f0610aa53408c/5C3114D8/t51.2885-15/e35/39361456_1151656778315071_3500535798078373888_n.jpg", "media_dim": "1080x1080", "media_location": "39361456_1151656778315071_3500535798078373888_n.jpg", "media_folder_location": "", "media_id": "1852581816939079391", "media_filename": "39361456_1151656778315071_3500535798078373888_n.jpg", "post_url": "https://www.instagram.com/p/Bm1sVjcAGbf/", "full_caption": "Comment your city you are in \ud83d\udc4d\nFollow: @blizzfact \u270c\n\ud83d\udc47\nTURN ON POST NOTIFICATIONS!\n\ud83d\udc46\n#sayingsandquotes #amazingfacts #whenitsreal #quickfact #factsss #factss #factsb #educateyourself #liveandlearn #positivethoughts #inspirationalwords #lifelesson #wordsoftheday #accurate #quotesgram #youknowit #mindblowing #truthseeker #betrue #factsonly #positivemind #humbleyourself #funnybuttrue #truuu #understand", "number_of_chars": 92, "number_of_words": 11, "hashtag_rank_list": [["quickfact"], ["factsb", "whenitsreal"], ["factsss", "amazingfacts", "factss"], [], ["humbleyourself", "sayingsandquotes", "funnybuttrue"], ["truuu", "wordsoftheday", "truthseeker", "mindblowing", "factsonly", "inspirationalwords", "youknowit"], ["educateyourself", "positivemind", "accurate", "betrue", "liveandlearn", "understand", "quotesgram", "lifelesson", "positivethoughts"], [], []], "hashtags": "inspirationalwords,sayingsandquotes,positivethoughts,educateyourself,humbleyourself,wordsoftheday,positivemind,liveandlearn,funnybuttrue,amazingfacts,truthseeker,mindblowing,whenitsreal,understand,quotesgram,lifelesson,quickfact,factsonly,youknowit,accurate,factsss,factsb,betrue,factss,truuu", "number_of_hashtags": 25, "emojis": "\ud83d\udc4d\u270c\ud83d\udc47\ud83d\udc46", "number_of_emojis": 4, "tagged_accounts": "", "number_of_tagged_accounts": 0, "location_url": "https://www.instagram.com/explore/locations/127958949/caesars-palace/", "date": "08/23/2018", "time": "22:56:23", "post_type": "image", "likes": 1272, "comments": 2, "mentions": "blizzfact", "mentions_count": 1, "weekday": "Thursday", "month": "August", "video_duration": null, "content_count": null, "video_views": null}, {"is_top_nine": false, "top_nine_rank": null, "location_name": "Caesars Palace", "location_id": "127958949", "media_size": "809.67,582.357,550.957,606.751", "download_url": "https://scontent-mrs1-1.cdninstagram.com/vp/af3d01f9c91cb5940c27ff93b6811b6e/5C15C4D2/t51.2885-15/e35/38938377_918388498370469_638799625624485888_n.jpg,https://scontent-mrs1-1.cdninstagram.com/vp/47f52a20c9f854d9bcc3e87a12edfca8/5C327240/t51.2885-15/e35/39962040_1314982548639076_3931025077440610304_n.jpg,https://scontent-mrs1-1.cdninstagram.com/vp/3a7fcfb7b8c113761980bfa6300e14d4/5C2156D0/t51.2885-15/e35/39128026_650480258685469_6680637237392048128_n.jpg,https://scontent-mrs1-1.cdninstagram.com/vp/ee5d931dff18bf156a95c849663a7845/5C2E575B/t51.2885-15/e35/39175453_1527622464051023_8539794125879246848_n.jpg", "media_dim": "1080x1080,1080x1080,1080x1080,1080x1080", "media_location": "gallery_1852497422316503896/38938377_918388498370469_638799625624485888_n.jpg,gallery_1852497422316503896/39962040_1314982548639076_3931025077440610304_n.jpg,gallery_1852497422316503896/39128026_650480258685469_6680637237392048128_n.jpg,gallery_1852497422316503896/39175453_1527622464051023_8539794125879246848_n.jpg", "media_folder_location": "gallery_1852497422316503896/", "media_id": "1852497422316503896", "media_filename": "38938377_918388498370469_638799625624485888_n.jpg,39962040_1314982548639076_3931025077440610304_n.jpg,39128026_650480258685469_6680637237392048128_n.jpg,39175453_1527622464051023_8539794125879246848_n.jpg", "post_url": "https://www.instagram.com/p/Bm1ZJc0gINY/", "full_caption": "Like if you enjoy reading facts \ud83e\udd13\n\ud83d\ude0e\n@blizzfact\n@blizzfact\n\ud83d\udc47\n#factsdaily #learnsomething #truthbetold\ud83d\udcaf #factsmatter #trueshit", "number_of_chars": 41, "number_of_words": 6, "hashtag_rank_list": [[], ["factsmatter"], ["truthbetold\ud83d\udcaf", "factsdaily"], ["learnsomething"], [], [], ["trueshit"], [], []], "hashtags": "learnsomething,truthbetold\ud83d\udcaf,factsmatter,factsdaily,trueshit", "number_of_hashtags": 5, "emojis": "\ud83e\udd13\ud83d\ude0e\ud83d\udc47\ud83d\udcaf", "number_of_emojis": 4, "tagged_accounts": "", "number_of_tagged_accounts": 0, "location_url": "https://www.instagram.com/explore/locations/127958949/caesars-palace/", "date": "08/23/2018", "time": "20:08:43", "post_type": "gallery", "likes": 1207, "comments": 2, "mentions": "blizzfact", "mentions_count": 1, "weekday": "Thursday", "month": "August", "video_duration": null, "content_count": 4, "video_views": null}, {"is_top_nine": false, "top_nine_rank": null, "location_name": "Premier Inn London Wembley Stadium", "location_id": "7853175", "media_size": "464.556", "download_url": "https://scontent-mrs1-1.cdninstagram.com/vp/97f60a3ad0b21c819b82489fe281309e/5C3A7247/t51.2885-15/e35/39371731_462328990916147_4020028447765037056_n.jpg", "media_dim": "1080x1080", "media_location": "39371731_462328990916147_4020028447765037056_n.jpg", "media_folder_location": "", "media_id": "1851655678293415758", "media_filename": "39371731_462328990916147_4020028447765037056_n.jpg", "post_url": "https://www.instagram.com/p/BmyZwdnA5dO/", "full_caption": "Like if you love dark chocolate. Comment if you like white chocolate \ud83d\ude1b\nFollow: @blizzfact \u270c\n\ud83d\udc47\nTURN ON POST NOTIFICATIONS!\n\ud83d\udc46\n#factsmatter #factsallday #questionmark #factset #factsornah #factsaboutlife #truthbetold\ud83d\udcaf #nojoke #realshittho #wikipedia #learn #didyouknow #staytruetoyourself #tootrue #beliveinyourself #lifelesson #questioneverything #truedat #itstrue #educateyourself #accurate #understand #realshit #lessonslearned #fact #wierd", "number_of_chars": 132, "number_of_words": 17, "hashtag_rank_list": [["factsaboutlife"], [], ["truthbetold\ud83d\udcaf"], [], ["realshittho", "wikipedia"], ["itstrue", "lessonslearned"], ["educateyourself", "didyouknow", "accurate"], [], ["realshit"]], "hashtags": "staytruetoyourself,questioneverything,beliveinyourself,educateyourself,lessonslearned,factsaboutlife,truthbetold\ud83d\udcaf,questionmark,realshittho,factsmatter,factsallday,didyouknow,factsornah,understand,lifelesson,wikipedia,accurate,realshit,itstrue,factset,tootrue,truedat,nojoke,learn,wierd,fact", "number_of_hashtags": 26, "emojis": "\ud83d\ude1b\u270c\ud83d\udc47\ud83d\udc46\ud83d\udcaf", "number_of_emojis": 5, "tagged_accounts": "", "number_of_tagged_accounts": 0, "location_url": "https://www.instagram.com/explore/locations/7853175/premier-inn-london-wembley-stadium/", "date": "08/22/2018", "time": "16:16:19", "post_type": "image", "likes": 1091, "comments": 3, "mentions": "blizzfact", "mentions_count": 1, "weekday": "Wednesday", "month": "August", "video_duration": null, "content_count": null, "video_views": null}, {"is_top_nine": false, "top_nine_rank": null, "location_name": "Manchester, Texas", "location_id": "388644372", "media_size": "521.142", "download_url": "https://scontent-mrs1-1.cdninstagram.com/vp/3a33096798a5aeacbb1fe71ce47741c5/5C24E581/t51.2885-15/e35/39255721_1923044831322909_5803259789156810752_n.jpg", "media_dim": "1080x1080", "media_location": "39255721_1923044831322909_5803259789156810752_n.jpg", "media_folder_location": "", "media_id": "1851021717179229090", "media_filename": "39255721_1923044831322909_5803259789156810752_n.jpg", "post_url": "https://www.instagram.com/p/BmwJnHUAGOi/", "full_caption": "Tag a friend who has a big nose \ud83d\udc4d\nFollow: @blizzfact before your friends did \ud83d\ude1b\n\ud83d\udc47\nTURN ON POST NOTIFICATIONS!\n\ud83d\udc46\n#factssss #factstho #dailypositivity #factsssss #truthhurts #itstrue #keepitreal #quotesgram #sadbuttrue #imjustsaying #truefact #knowledgeispower #knowledge #believing #facts #funnybuttrue", "number_of_chars": 110, "number_of_words": 17, "hashtag_rank_list": [[], ["factsssss", "factssss"], ["dailypositivity"], ["factstho"], ["funnybuttrue", "believing"], ["truefact", "itstrue", "imjustsaying", "truthhurts"], ["quotesgram", "sadbuttrue", "knowledgeispower", "keepitreal"], [], ["facts", "knowledge"]], "hashtags": "knowledgeispower,dailypositivity,funnybuttrue,imjustsaying,quotesgram,sadbuttrue,truthhurts,keepitreal,factsssss,knowledge,believing,truefact,factstho,factssss,itstrue,facts", "number_of_hashtags": 16, "emojis": "\ud83d\udc4d\ud83d\ude1b\ud83d\udc47\ud83d\udc46", "number_of_emojis": 4, "tagged_accounts": "", "number_of_tagged_accounts": 0, "location_url": "https://www.instagram.com/explore/locations/388644372/manchester-texas/", "date": "08/21/2018", "time": "19:16:45", "post_type": "image", "likes": 1580, "comments": 11, "mentions": "blizzfact", "mentions_count": 1, "weekday": "Tuesday", "month": "August", "video_duration": null, "content_count": null, "video_views": null}, {"is_top_nine": false, "top_nine_rank": null, "location_name": "Los Angeles, California", "location_id": "212999109", "media_size": "238.235,647.489,628.224,506.088,320.972", "download_url": "https://scontent-mrs1-1.cdninstagram.com/vp/b5062969c0b4be928bfa255d70a946c2/5C2D5810/t51.2885-15/e35/38618288_225182374828538_3621228467904839680_n.jpg,https://scontent-mrs1-1.cdninstagram.com/vp/52c1da8b2bf6e53c4936597366edfa89/5BFF5749/t51.2885-15/e35/39013986_255905235052278_6516497447198392320_n.jpg,https://scontent-mrs1-1.cdninstagram.com/vp/c92b563499eab80d0a07fb50d6628395/5C3B1C53/t51.2885-15/e35/38773349_2119170088115701_7834694657769472_n.jpg,https://scontent-mrs1-1.cdninstagram.com/vp/ce5aaf1109091b43c640c873ff987c00/5C14505C/t51.2885-15/e35/39296793_294876521318983_5848534297849364480_n.jpg,https://scontent-mrs1-1.cdninstagram.com/vp/847a4a281d64ea742d77ae98eecf8ea8/5C1A9E16/t51.2885-15/e35/38860125_238739856827177_3564042640510943232_n.jpg", "media_dim": "1080x1080,1080x1080,1080x1080,1080x1080,1080x1080", "media_location": "gallery_1850326494782599296/38618288_225182374828538_3621228467904839680_n.jpg,gallery_1850326494782599296/39013986_255905235052278_6516497447198392320_n.jpg,gallery_1850326494782599296/38773349_2119170088115701_7834694657769472_n.jpg,gallery_1850326494782599296/39296793_294876521318983_5848534297849364480_n.jpg,gallery_1850326494782599296/38860125_238739856827177_3564042640510943232_n.jpg", "media_folder_location": "gallery_1850326494782599296/", "media_id": "1850326494782599296", "media_filename": "38618288_225182374828538_3621228467904839680_n.jpg,39013986_255905235052278_6516497447198392320_n.jpg,38773349_2119170088115701_7834694657769472_n.jpg,39296793_294876521318983_5848534297849364480_n.jpg,38860125_238739856827177_3564042640510943232_n.jpg", "post_url": "https://www.instagram.com/p/BmtriTAArCA/", "full_caption": "Comment your city \u26f0\ufe0f\n\ud83d\udc47\n@blizzfact\n@blizzfact\n\ud83d\ude0e\n#facts\ud83d\udcaf\ud83d\udcaf\ud83d\udcaf #factss #imnotanoption #instafacts #factsnotfear #pretend #educateyourself", "number_of_chars": 30, "number_of_words": 4, "hashtag_rank_list": [["imnotanoption"], [], ["factss"], ["instafacts"], ["facts\ud83d\udcaf\ud83d\udcaf\ud83d\udcaf"], ["pretend"], ["educateyourself"], [], []], "hashtags": "educateyourself,imnotanoption,factsnotfear,instafacts,facts\ud83d\udcaf\ud83d\udcaf\ud83d\udcaf,pretend,factss", "number_of_hashtags": 7, "emojis": "\u26f0\ud83d\udc47\ud83d\ude0e\ud83d\udcaf\ud83d\udcaf\ud83d\udcaf", "number_of_emojis": 6, "tagged_accounts": "", "number_of_tagged_accounts": 0, "location_url": "https://www.instagram.com/explore/locations/212999109/los-angeles-california/", "date": "08/20/2018", "time": "20:15:28", "post_type": "gallery", "likes": 1005, "comments": 4, "mentions": "blizzfact", "mentions_count": 1, "weekday": "Monday", "month": "August", "video_duration": null, "content_count": 5, "video_views": null}]